{
  "Records": [
    {
      "messageId": "19dd0b57-b21e-4ac1-bd88-01bbb068cb78",
      "receiptHandle": "MessageReceiptHandle",
      "body": {
        "AssetId": "gVELQZtOa1sApbeC",
        "JobId": "5ae668af-bf26-419d-9550-66926aa7053c",
        "TraceId": "d229a830-10a3-4179-a1e1-9ed68b62d6f7",
        "OssKey": "CHC/Pfizer/[XZBJ项目]-2019年Q3Q4浙江数据交付表.xlsx",
        "FileType": "xlsx",
        "FileName": "[XZBJ项目]-2019年Q3Q4浙江数据交付表.xlsx",
        "SheetName": "Sheet 1",
        "Owner": "test",
        "CreateTime": 1591698072699,
        "Labels": [
          "原始数据"
        ],
        "DataCover": [
          "201906"
        ],
        "GeoCover": [],
        "Markets": [],
        "Molecules": [
          "Amgen",
          "CPA"
        ],
        "Providers": []
      },
      "attributes": {
        "ApproximateReceiveCount": "1",
        "SentTimestamp": "1523232000000",
        "SenderId": "123456789012",
        "ApproximateFirstReceiveTimestamp": "1523232000001"
      },
      "messageAttributes": {
        "type": {
          "stringValue": "PushJob",
          "stringListValues": [],
          "binaryListValues": [],
          "dataType": "String"
        },
        "jobId": {
          "stringValue": "0x001",
          "stringListValues": [],
          "binaryListValues": [],
          "dataType": "String"
        },
        "traceId": {
          "stringValue": "0x001",
          "stringListValues": [],
          "binaryListValues": [],
          "dataType": "String"
        }
      },
      "md5OfBody": "7b270e59b47ff90a553787216d55d91d",
      "eventSource": "aws:sqs",
      "eventSourceARN": "arn:aws-cn:sqs:cn-northwest-1:123456789012:MyQueue",
      "awsRegion": "cn-northwest-1"
    }
  ]
}